dev/__init__.py
dev/example01.py
dev/example02.py
dev/example03.py
dgm1/__init__.py
dgm1/dgm1_nrw.py
test/__init__.py
test/dgm1_test.py
test/example01.py
test/example02.py
test/example03.py
test/example_av.py
dgm1-0.0.4.dist-info/LICENSE
dgm1-0.0.4.dist-info/METADATA
dgm1-0.0.4.dist-info/WHEEL
dgm1-0.0.4.dist-info/top_level.txt
dgm1-0.0.4.dist-info/RECORD
